Workbook

Sheet practicas
A1: total_goles_historia | B1: 5500
A2: total_goles_ 1970 | B2: 120
A3: total_goles_2026 | B3: =B2*1 -> 120
A4: porcentaje de goles en 2026 | B4: =(B2*C6)/B1 -> 2.1818182
A6: total | B6: 5500 | C6: 100
A7: muestra | B7: 120 | C7: x
A12: gasto_combustible_año | B12: 2300
A13: enero | B13: 300
A14: febrero
A15: marzo
A16: abril
A17: mayo
A18: junio | B18: =B12*B20 -> 300
A20: porcentaje | B20: =B13/B12 -> 0.13043478
B21: caramelos
A22: media aritmetica
A23: juan | B23: 12
A24: pablo | B24: 3
A25: paula | B25: 34
A26: david | B26: 2
A27: miriam | B27: 100
A29: cantidad total de caramelos | B29: =SUM(B23:B27) -> 151
A30: media aritmetica | B30: =AVERAGE(B23,B24,B25,B26,B27) -> 30.2 | C30: =B29/B31 -> 30.2
A31: cantidad personas | B31: =COUNTA(A23:A27) -> 5 | E31: cantidad total | F31: =SUM(B23:B27) -> 151
E32: cantidad muestra (numero personas)
E33: media

Sheet media
A1: juan | B1: 12
A2: pablo | B2: 3
A3: paula | B3: 34
A4: david | B4: 2
A5: miriam | B5: 100
A6: mario | B6: 12
A7: reniel | B7: 35
A8: joaquin | B8: 13
E10: cantidad total | F10: =SUM(B:B) -> 211
E11: cantidad muestra (numero personas) | F11: =COUNTA(A:A) -> 8
E12: media(promedio) | F12: =F10/F11 -> 26.375 | G12: =AVERAGE(B:B,B2,B3,B4,B5,B6,B7) -> 28.357143
E13: redondeo a la alta | F13: =ROUNDUP(F12,0) -> 27
E14: redondeo a la baja | F14: =ROUNDDOWN(F12,0) -> 26
E15: redondeo | F15: =ROUND(F12,0) -> 26

Sheet mediana
A1: reniel | B1: 4
A2: david | B2: 5 | D2: mediana | E2: =MEDIAN(B:B) -> 13
A3: miguel | B3: 10
A4: lara | B4: 12
A5: mario | B5: 13
A6: luis | B6: 15
A7: paula | B7: 20
A8: pablo | B8: 80
A9: miriam | B9: 120

Sheet ejemplo3
A1: garg | B1: 100
A2: zog | B2: 12
A3: puff | B3: 8
A4: moco | B4: 5
A5: bloog | B5: 3
D6: mediana | E6: =MEDIAN(B:B) -> 8

Sheet ejemplo4_tabla_sueldos
A1: recepcionista | B1: 18000
A2: programador_junior1 | B2: 20000
A3: programador_junior2 | B3: 30000
A4: programador senior | B4: 40000
A5: jefe_proyecto | B5: 35000
A6: directora financiera | B6: 60000
A7: directora ventas | B7: 89000
A8: ceo/dueño empresa | B8: 300000

Sheet ejemplo4_tabla_totales
A1: media | B1: =AVERAGE(ejemplo4_tabla_sueldos!B:B) -> 74000 | C1: retencion | D1: 0.18
A2: mediana | B2: =MEDIAN(ejemplo4_tabla_sueldos!B:B) -> 37500
A3: pagas | B3: 12

Sheet ejemplo4_tabla_pagas
B1: antes retencion(bruto) | C1: despues retencion(neto)
A2: enero | B2: =AVERAGE(ejemplo4_tabla_totales!$B$2/ejemplo4_tabla_totales!$B$3) -> 3125 | C2: =B2-(B2*ejemplo4_tabla_totales!$D$1) -> 2562.5
A3: febrero | B3: =AVERAGE(ejemplo4_tabla_totales!$B$2/ejemplo4_tabla_totales!$B$3) -> 3125 | C3: =B3-(B3*ejemplo4_tabla_totales!$D$1) -> 2562.5
A4: marzo | B4: =AVERAGE(ejemplo4_tabla_totales!$B$2/ejemplo4_tabla_totales!$B$3) -> 3125 | C4: =B4-(B4*ejemplo4_tabla_totales!$D$1) -> 2562.5
A5: abril | B5: =AVERAGE(ejemplo4_tabla_totales!$B$2/ejemplo4_tabla_totales!$B$3) -> 3125 | C5: =B5-(B5*ejemplo4_tabla_totales!$D$1) -> 2562.5
A6: mayo | B6: =AVERAGE(ejemplo4_tabla_totales!$B$2/ejemplo4_tabla_totales!$B$3) -> 3125 | C6: =B6-(B6*ejemplo4_tabla_totales!$D$1) -> 2562.5
A7: junio | B7: =AVERAGE(ejemplo4_tabla_totales!$B$2/ejemplo4_tabla_totales!$B$3) -> 3125 | C7: =B7-(B7*ejemplo4_tabla_totales!$D$1) -> 2562.5
A8: julio | B8: =AVERAGE(ejemplo4_tabla_totales!$B$2/ejemplo4_tabla_totales!$B$3) -> 3125 | C8: =B8-(B8*ejemplo4_tabla_totales!$D$1) -> 2562.5
A9: agosto | B9: =AVERAGE(ejemplo4_tabla_totales!$B$2/ejemplo4_tabla_totales!$B$3) -> 3125 | C9: =B9-(B9*ejemplo4_tabla_totales!$D$1) -> 2562.5
A10: septiembre | B10: =AVERAGE(ejemplo4_tabla_totales!$B$2/ejemplo4_tabla_totales!$B$3) -> 3125 | C10: =B10-(B10*ejemplo4_tabla_totales!$D$1) -> 2562.5
A11: octubre | B11: =AVERAGE(ejemplo4_tabla_totales!$B$2/ejemplo4_tabla_totales!$B$3) -> 3125 | C11: =B11-(B11*ejemplo4_tabla_totales!$D$1) -> 2562.5
A12: noviembre | B12: =AVERAGE(ejemplo4_tabla_totales!$B$2/ejemplo4_tabla_totales!$B$3) -> 3125 | C12: =B12-(B12*ejemplo4_tabla_totales!$D$1) -> 2562.5
A13: diciembre | B13: =AVERAGE(ejemplo4_tabla_totales!$B$2/ejemplo4_tabla_totales!$B$3) -> 3125 | C13: =B13-(B13*ejemplo4_tabla_totales!$D$1) -> 2562.5
A14: total | B14: =SUM(B2:B13) -> 37500 | C14: =SUM(C2:C13) -> 30750 | D14: =B14-C14 -> 6750 | E14: diferencia despues de impuestos

Sheet moda
A1: negro
A2: azul
A3: rosa
A4: rojo
A5: verde
A6: verde | C6: azul | D6: 2 | E6: =COUNTIF(A:A,C6) -> 2
A7: rosa | C7: negro | D7: 3 | E7: =COUNTIF(A:A,C7) -> 3
A8: negro | C8: rosa | D8: 4 | E8: =COUNTIF(A:A,C8) -> 4 | G8: moda | H8: formula de excel antigüa, solo vale para numeros | I8: devuelve el primer valor que lo cumpla
A9: blanco | C9: verde | D9: 3 | E9: =COUNTIF(A:A,C9) -> 3 | G9: moda.uno | H9: formula excel moderna pero solo vale para numeros | I9: devuelve el primer valor que lo cumpla
A10: gris | C10: gris | D10: 1 | E10: =COUNTIF(A:A,C10) -> 1 | G10: moda.varios | H10: formula excel moderna , solo vale para numeros | I10: devuelve todas las posibilidades
A11: azul | C11: blanco | D11: 1 | E11: =COUNTIF(A:A,C11) -> 1 | G11: contar.si(muestra;valor) | H11: vale para caracteres
A12: negro | C12: rojo | D12: 1 | E12: =COUNTIF(A:A,C12) -> 1
A13: rosa
A14: verde | D14: max | E14: =MAX(E6:E12) -> 4 | G14: maximo | H14: max: calcula el valor maximo de un conjunto
A15: rosa | G15: minimo | H15: min: calcula el valor minimo de un conjunto

Sheet ejemplo5
A1: talla_zapatillas | B1: pares_vendidos_semana
A2: talla 36 | B2: 4
A3: talla 37 | B3: 7
A4: talla 38 | B4: 15
A5: talla 39 | B5: 12
A6: talla 40 | B6: 15
A7: talla 41 | B7: 3
C10: ¿Cuál es la moda o modas de la talla de zapatillas vendidas? | D10: =MAX(B2:B7) -> 15 | E10: {=_xlfn.MODE.MULT(B2:B7)} -> 15 | F10: {=_xlfn._xlws.FILTER(A2:A7,B2:B7=D10)} -> talla 38
C11: la moda es 15¿ por que se equivoca el empleado nuevo? | D11: no | E11: si se equivoca el empleado, porque la moda no es 15 es la talla correspondiente | F11: talla 40
C12: como encargado de la tienda ¿Qué decision tomarias basandote en el resultado de la moda? | D12: comprar más pares de esas tallas

Sheet percentiles
A1: 120
A2: 135
A3: 145
A4: 150
A5: 155 | C5: percentil_5 | D5: 155
A6: 175 | C6: percentil_3 | D6: 145
A7: 180 | C7: percentil_7 | D7: 180
A8: 185 | D8: =MEDIAN(A:A) -> 155 | G8: percentil excel | H8: =_xlfn.PERCENTILE.INC(A:A,100%) -> 190
A9: 190

Sheet cuartiles
A1: 120 | C1: cuartil 0 | D1: 0 | E1: q0 | F1: =_xlfn.QUARTILE.INC(A:A,0) -> 120 | H1: =_xlfn.QUARTILE.EXC(A:A,0) -> #NUM!
A2: 135 | C2: primer cuartil | D2: 0.25 | E2: q1 | F2: =_xlfn.QUARTILE.INC(A:A,1) -> 145 | H2: =_xlfn.QUARTILE.EXC(A:A,1) -> 140
A3: 145 | C3: segundo cuartil | D3: 0.5 | E3: q2 | F3: =_xlfn.QUARTILE.INC(A:A,2) -> 155 | H3: =_xlfn.QUARTILE.EXC(A:A,2) -> 155
A4: 150 | C4: tercer cuartil | D4: 0.75 | E4: q3 | F4: =_xlfn.QUARTILE.INC(A:A,3) -> 180 | H4: =_xlfn.QUARTILE.EXC(A:A,3) -> 182.5
A5: 155 | C5: cuarto cuartil | D5: 1 | E5: q4 | F5: =_xlfn.QUARTILE.INC(A:A,4) -> 190 | H5: =_xlfn.QUARTILE.EXC(A:A,4) -> #NUM!
A6: 175
A7: 180
A8: 185
A9: 190

Sheet rango
A1: pan | B1: 0.7
A2: leche | B2: 2.4
A3: huevos | B3: 3.5
A4: carne | B4: 8.9
A5: coliflor | B5: 1
A6: apio | B6: 1
A7: tomate | B7: 5.3
A8: cebolla | B8: 1.25 | D8: {=_xlfn._xlws.FILTER(A:A,B:B=E8)} -> pescado | E8: =MAX(B:B) -> 35 | F8: max
A9: pescado | B9: 35 | D9: {=_xlfn._xlws.FILTER(A:A,B:B=E9)} -> pan | E9: =MIN(B:B) -> 0.7 | F9: min
D14: rango | E14: =E8-E9 -> 34.3 | F14: maximo - minimo

Sheet probabilidad
A1: tipo | B1: ventas
A2: calzado | B2: 15
A3: ropa | B3: 45
A4: accesorios | B4: 10
A6: totales | B6: =SUM(B2:B4) -> 70
A8: probabilidad venta calzado | B8: =B2/B6 -> 0.21428571 | C8: =B2/B6 -> 0.21428571
A9: probabilidad venta ropa | B9: =B3/B6 -> 0.64285714 | C9: =B3/B7 -> #DIV/0!
A10: probabilidad venta accesorios | B10: =B4/B6 -> 0.14285714 | C10: =B4/B8 -> 46.666667
B11: =SUM(B8:B10) -> 1 | C11: =SUM(C8:C10) -> #DIV/0!
